storm_indicator_pyqt/__init__.py
storm_indicator_pyqt/__main__.py
storm_indicator_pyqt/main.py
storm_indicator_pyqt/storm_ind.py
storm_indicator_pyqt/icons/tray.svg
storm_indicator_pyqt-1.2.1.dist-info/LICENSE
storm_indicator_pyqt-1.2.1.dist-info/METADATA
storm_indicator_pyqt-1.2.1.dist-info/WHEEL
storm_indicator_pyqt-1.2.1.dist-info/entry_points.txt
storm_indicator_pyqt-1.2.1.dist-info/top_level.txt
storm_indicator_pyqt-1.2.1.dist-info/RECORD
