Metadata-Version: 2.1
Name: storm-indicator-pyqt
Version: 1.2.1
Summary: PyQt based indicator for connecting to your SSH connections easily.
Home-page: https://github.com/olegbuevich/storm-indicator
Author: Oleg Buevich
Author-email: gangs1989@gmail.com
License: MIT
Platform: UNKNOWN
Classifier: Programming Language :: Python :: 3
Classifier: License :: OSI Approved :: MIT License
Classifier: Operating System :: MacOS
Classifier: Operating System :: POSIX
Classifier: Operating System :: Unix
Classifier: Topic :: System :: Systems Administration
Requires-Dist: stormssh
Requires-Dist: PyQt5
Requires-Dist: envparse
